objackson/__init__.py
objackson/__main__.py
objackson/json_object.py
objackson/serializer.py
Objackson-1.0.1.dist-info/LICENSE
Objackson-1.0.1.dist-info/METADATA
Objackson-1.0.1.dist-info/WHEEL
Objackson-1.0.1.dist-info/top_level.txt
Objackson-1.0.1.dist-info/RECORD
