Metadata-Version: 2.1
Name: Objackson
Version: 1.0.1
Summary: A JSON serializer for Python
Home-page: https://github.com/sv-giampa/Objackson
Author: 'Salvatore Giampà'
License: Apache License version 2.0
Keywords: json,serializer,deserializer,serialization,deserialization,object
Classifier: Programming Language :: Python :: 3 :: Only
Classifier: License :: OSI Approved :: Apache Software License
Classifier: Topic :: Software Development :: Libraries
Classifier: Topic :: File Formats :: JSON
Requires-Python: >=3.8.0
License-File: LICENSE
